tea_tasting-1.5.1.dist-info/METADATA
tea_tasting-1.5.1.dist-info/WHEEL
tea_tasting-1.5.1.dist-info/entry_points.txt
tea_tasting-1.5.1.dist-info/licenses/LICENSE
tea_tasting/__init__.py
tea_tasting/_version.txt
tea_tasting/aggr.py
tea_tasting/config.py
tea_tasting/datasets.py
tea_tasting/experiment.py
tea_tasting/metrics/__init__.py
tea_tasting/metrics/base.py
tea_tasting/metrics/mean.py
tea_tasting/metrics/proportion.py
tea_tasting/metrics/resampling.py
tea_tasting/multiplicity.py
tea_tasting/utils.py
tea_tasting/version.py
tea_tasting-1.5.1.dist-info/RECORD
