Metadata-Version: 2.1
Name: tea-tasting
Version: 1.5.1
Summary: A Python package for the statistical analysis of A/B tests.
Author-Email: Evgeny Ivanov <ivanov.evgeny.n@gmail.com>
License: MIT
Classifier: Development Status :: 5 - Production/Stable
Classifier: Intended Audience :: Developers
Classifier: Intended Audience :: Information Technology
Classifier: Intended Audience :: Science/Research
Classifier: License :: OSI Approved
Classifier: License :: OSI Approved :: MIT License
Classifier: Operating System :: OS Independent
Classifier: Programming Language :: Python
Classifier: Programming Language :: Python :: 3
Classifier: Programming Language :: Python :: 3.10
Classifier: Programming Language :: Python :: 3.11
Classifier: Programming Language :: Python :: 3.12
Classifier: Programming Language :: Python :: 3.13
Classifier: Programming Language :: Python :: 3.14
Classifier: Topic :: Scientific/Engineering
Classifier: Topic :: Scientific/Engineering :: Information Analysis
Classifier: Topic :: Scientific/Engineering :: Mathematics
Classifier: Typing :: Typed
Project-URL: homepage, https://tea-tasting.e10v.me
Project-URL: documentation, https://tea-tasting.e10v.me/user-guide
Project-URL: source, https://github.com/e10v/tea-tasting
Project-URL: release notes, https://github.com/e10v/tea-tasting/releases
Requires-Python: >=3.10
Requires-Dist: ibis-framework>=9
Requires-Dist: narwhals>=1.4
Requires-Dist: numpy>=1.25
Requires-Dist: pyarrow>=16
Requires-Dist: scipy>=1.11
